datacanva/__init__.py
datacanva/api/__init__.py
datacanva/api/content_hub.py
datacanva/api/warehouse.py
datacanva/service/__init__.py
datacanva/service/content_hub.py
datacanva/service/warehouse.py
datacanva/type/criteria.py
datacanva/type/expression_tree.py
datacanva/type/warehouse.py
datacanva-1.0.0.dist-info/METADATA
datacanva-1.0.0.dist-info/WHEEL
datacanva-1.0.0.dist-info/licenses/LICENSE
datacanva-1.0.0.dist-info/RECORD
