Metadata-Version: 2.4
Name: datacanva
Version: 1.0.0
Summary: Python module which connects to the DataCanva REST API
Author-email: Lively Impact Technology Limited <info@livelyimpact.com>
License-Expression: MIT
License-File: LICENSE
Classifier: Operating System :: OS Independent
Classifier: Programming Language :: Python :: 3
Requires-Python: >=3.9
Requires-Dist: pandas>=2.3.3
Requires-Dist: pyjson5>=2.0.0
Requires-Dist: requests>=2.28.1
